NagiosCheckHelper/__init__.py
NagiosCheckHelper/tests/__init__.py
NagiosCheckHelper/tests/test_NagErrors.py
NagiosCheckHelper/tests/test_NagEval.py
NagiosCheckHelper-0.1.5.dist-info/LICENSE
NagiosCheckHelper-0.1.5.dist-info/METADATA
NagiosCheckHelper-0.1.5.dist-info/WHEEL
NagiosCheckHelper-0.1.5.dist-info/top_level.txt
NagiosCheckHelper-0.1.5.dist-info/RECORD
