Metadata-Version: 2.1
Name: NagiosCheckHelper
Version: 0.1.5
Summary: Nagios Helper Objects for Python Check Scripts
Home-page: https://github.com/paradxum/NagiosCheckHelper
Author: Eric Schultz
Author-email: eric.schultz@cyvon.com
License: UNKNOWN
Platform: UNKNOWN
Classifier: Programming Language :: Python :: 3
Classifier: License :: OSI Approved :: GNU General Public License v3 (GPLv3)
Classifier: Operating System :: OS Independent
Requires-Python: >=3.1
License-File: LICENSE
